mdx_forge_links.py
test_forge_links.py
mdx_forge_links-0.5.dist-info/LICENSE
mdx_forge_links-0.5.dist-info/METADATA
mdx_forge_links-0.5.dist-info/WHEEL
mdx_forge_links-0.5.dist-info/RECORD
