Metadata-Version: 2.3
Name: mdx-forge-links
Version: 0.5
Summary: An extension to Python-Markdown which adds support for shorthand links to your software forge's users, repositories, issues and commits.
License: BSD-3-Clause
Keywords: markdown,python-markdown,forge
Author: Tobias Bölz
Author-email: tobias@boelz.eu
Requires-Python: >=3.9,<4.0
Classifier: Development Status :: 4 - Beta
Classifier: Operating System :: OS Independent
Classifier: Programming Language :: Python
Classifier: Programming Language :: Python :: 3
Classifier: Programming Language :: Python :: 3.9
Classifier: Programming Language :: Python :: 3.10
Classifier: Programming Language :: Python :: 3.11
Classifier: Programming Language :: Python :: 3.12
Classifier: Programming Language :: Python :: 3.13
Classifier: Programming Language :: Python :: Implementation :: CPython
Classifier: Programming Language :: Python :: Implementation :: PyPy
Classifier: Topic :: Documentation
Classifier: Topic :: Text Processing
Classifier: Topic :: Text Processing :: Markup
Classifier: Topic :: Text Processing :: Markup :: HTML
Requires-Dist: markdown (>=3.0.0)
Project-URL: Changelog, https://git.boelz.eu/tmb/mdx-forge-links#changelog
Project-URL: Homepage, https://git.boelz.eu/tmb/mdx-forge-links
Project-URL: Issue Tracker, https://git.boelz.eu/tmb/mdx-forge-links/issues
Project-URL: Repository, https://git.boelz.eu/tmb/mdx-forge-links
